rest_framework_dyn_serializer.py
setup.cfg
setup.py
rest_framework_dyn_serializer.egg-info/PKG-INFO
rest_framework_dyn_serializer.egg-info/SOURCES.txt
rest_framework_dyn_serializer.egg-info/dependency_links.txt
rest_framework_dyn_serializer.egg-info/requires.txt
rest_framework_dyn_serializer.egg-info/top_level.txt