Metadata-Version: 1.1
Name: rest-framework-dyn-serializer
Version: 1.3.1
Summary: Dynamic serializer for Django REST framework
Home-page: https://github.com/Nepherhotep/django-rest-framework-dyn-serializer
Author: Alexey Zankevich
Author-email: alex.zankevich@gmail.com
License: MIT
Keywords: Django,REST,DRF
Platform: Platform Independent
Classifier: Framework :: Django :: 1.9
Classifier: Development Status :: 5 - Production/Stable
Classifier: Programming Language :: Python :: 2.7
Classifier: Programming Language :: Python :: 3.5
